pymusement/__init__.py
pymusement/attraction.py
pymusement/park.py
pymusement/ride.py
pymusement/show.py
pymusement/config/__init__.py
pymusement/config/disneyparis.py
pymusement/config/usj.py
pymusement/parks/HersheyPark.py
pymusement/parks/__init__.py
pymusement/parks/disney/AnimalKingdom.py
pymusement/parks/disney/CaliforniaAdventure.py
pymusement/parks/disney/DisneyPark.py
pymusement/parks/disney/Disneyland.py
pymusement/parks/disney/Epcot.py
pymusement/parks/disney/HollywoodStudios.py
pymusement/parks/disney/MagicKingdom.py
pymusement/parks/disney/__init__.py
pymusement/parks/seaworld/BuschGardensTampa.py
pymusement/parks/seaworld/BuschGardensWilliamsburg.py
pymusement/parks/seaworld/SeaworldOrlando.py
pymusement/parks/seaworld/SeaworldPark.py
pymusement/parks/seaworld/SeaworldSanAntonio.py
pymusement/parks/seaworld/SeaworldSanDiego.py
pymusement/parks/seaworld/__init__.py
pymusement/parks/sixflags/LaRondeMontreal.py
pymusement/parks/sixflags/SixFlagsAmerica.py
pymusement/parks/sixflags/SixFlagsDarienLake.py
pymusement/parks/sixflags/SixFlagsDiscoveryKingdom.py
pymusement/parks/sixflags/SixFlagsFiestaTexas.py
pymusement/parks/sixflags/SixFlagsFrontierCity.py
pymusement/parks/sixflags/SixFlagsGreatAdventure.py
pymusement/parks/sixflags/SixFlagsGreatAmerica.py
pymusement/parks/sixflags/SixFlagsHurricaneHarborArlington.py
pymusement/parks/sixflags/SixFlagsHurricaneHarborChicago.py
pymusement/parks/sixflags/SixFlagsHurricaneHarborConcord.py
pymusement/parks/sixflags/SixFlagsHurricaneHarborJackson.py
pymusement/parks/sixflags/SixFlagsHurricaneHarborLosAngeles.py
pymusement/parks/sixflags/SixFlagsHurricaneHarborOaxtepec.py
pymusement/parks/sixflags/SixFlagsHurricaneHarborOklahomaCity.py
pymusement/parks/sixflags/SixFlagsHurricaneHarborPhoenix.py
pymusement/parks/sixflags/SixFlagsHurricaneHarborRockford.py
pymusement/parks/sixflags/SixFlagsHurricaneHarborSplashTown.py
pymusement/parks/sixflags/SixFlagsMagicMountain.py
pymusement/parks/sixflags/SixFlagsMexico.py
pymusement-0.6.2.dist-info/METADATA
pymusement-0.6.2.dist-info/WHEEL
pymusement-0.6.2.dist-info/entry_points.txt
pymusement-0.6.2.dist-info/licenses/LICENSE
pymusement-0.6.2.dist-info/RECORD
